wpscan/__init__.py
wpscan/cli.py
wpscan-0.5.dist-info/METADATA
wpscan-0.5.dist-info/WHEEL
wpscan-0.5.dist-info/entry_points.txt
wpscan-0.5.dist-info/top_level.txt
wpscan-0.5.dist-info/RECORD
