Metadata-Version: 2.1
Name: wpscan
Version: 0.5
